make_voc_dataset/__init__.py
make_voc_dataset/make_voc_dataset.py
make_voc_dataset-0.0.5.dev2.dist-info/LICENSE
make_voc_dataset-0.0.5.dev2.dist-info/METADATA
make_voc_dataset-0.0.5.dev2.dist-info/WHEEL
make_voc_dataset-0.0.5.dev2.dist-info/entry_points.txt
make_voc_dataset-0.0.5.dev2.dist-info/top_level.txt
make_voc_dataset-0.0.5.dev2.dist-info/RECORD
