Metadata-Version: 2.1
Name: make-voc-dataset
Version: 0.0.5.dev2
Summary: A quick tool to make VOC style Dataset
Home-page: https://github.com/Razin-Tailor/make_voc_dataset
Author: Razin Tailor
Author-email: razintailorpy@gmail.com
License: UNKNOWN
Project-URL: Bug Tracker, https://github.com/Razin-Tailor/make_voc_dataset/issues
Platform: UNKNOWN
Classifier: Programming Language :: Python :: 3
Classifier: License :: OSI Approved :: MIT License
Classifier: Operating System :: OS Independent
Requires-Python: >=3.6
License-File: LICENSE
Requires-Dist: mmcv-full
Requires-Dist: numpy
Requires-Dist: setuptools (>=42)
Requires-Dist: tqdm
Requires-Dist: wheel
